README.rst
setup.py
spydaap/__init__.py
spydaap/cache.py
spydaap/cli.py
spydaap/containers.py
spydaap/daap.py
spydaap/daap_data.py
spydaap/metadata.py
spydaap/playlists.py
spydaap/server.py
spydaap/zeroconfimpl.py
spydaap.egg-info/PKG-INFO
spydaap.egg-info/SOURCES.txt
spydaap.egg-info/dependency_links.txt
spydaap.egg-info/entry_points.txt
spydaap.egg-info/requires.txt
spydaap.egg-info/top_level.txt
spydaap/parser/__init__.py
spydaap/parser/avi.py
spydaap/parser/flac.py
spydaap/parser/mov.py
spydaap/parser/mp3.py
spydaap/parser/ogg.py
spydaap/parser/vorbis.py