Metadata-Version: 1.1
Name: spydaap
Version: 0.2
Summary: A simple DAAP server
Home-page: https://github.com/egh/spydaap
Author: Erik Hetzner
Author-email: egh@e6h.org
License: UNKNOWN
Platform: UNKNOWN
Classifier: Development Status :: 4 - Beta
Classifier: License :: OSI Approved :: GNU General Public License (GPL)
Classifier: Programming Language :: Python
Classifier: Topic :: Multimedia :: Sound/Audio
Classifier: Operating System :: POSIX
Classifier: Intended Audience :: End Users/Desktop
